_griddb_python.cpython-310-x86_64-linux-gnu.so
griddb_python.py
hello_cam-1.1.1.dist-info/LICENSE
hello_cam-1.1.1.dist-info/METADATA
hello_cam-1.1.1.dist-info/WHEEL
hello_cam-1.1.1.dist-info/top_level.txt
hello_cam-1.1.1.dist-info/RECORD
