Metadata-Version: 2.1
Name: hello-cam
Version: 1.1.1
Summary: simple public
Home-page: https://github.com/nguyentientungduong/pypi_public/
Author: Duong NTT
Author-email: contact@duong.org
License: Apache Software License
Platform: UNKNOWN
Classifier: License :: OSI Approved :: Apache Software License
Classifier: Operating System :: POSIX :: Linux
Classifier: Programming Language :: Python :: 3.10
License-File: LICENSE
